{"trial_id": "66ffb16176d29440b39fc7080b0a55a7", "hyperparameters": {"space": [{"class_name": "Int", "config": {"name": "units_1", "default": null, "conditions": [], "min_value": 8, "max_value": 196, "step": 4, "sampling": null}}, {"class_name": "Float", "config": {"name": "regs_1", "default": 0.001, "conditions": [], "min_value": 0.001, "max_value": 0.1, "step": 0.001, "sampling": null}}, {"class_name": "Float", "config": {"name": "dropout_1", "default": 0.1, "conditions": [], "min_value": 0.1, "max_value": 0.8, "step": 0.001, "sampling": null}}, {"class_name": "Int", "config": {"name": "units_2", "default": null, "conditions": [], "min_value": 8, "max_value": 196, "step": 4, "sampling": null}}, {"class_name": "Float", "config": {"name": "regs_2", "default": 0.001, "conditions": [], "min_value": 0.001, "max_value": 0.1, "step": 0.001, "sampling": null}}, {"class_name": "Float", "config": {"name": "dropout_2", "default": 0.1, "conditions": [], "min_value": 0.1, "max_value": 0.8, "step": 0.001, "sampling": null}}, {"class_name": "Int", "config": {"name": "units_4", "default": null, "conditions": [], "min_value": 8, "max_value": 196, "step": 4, "sampling": null}}, {"class_name": "Choice", "config": {"name": "learning_rate", "default": 0.1, "conditions": [], "values": [0.1, 0.01, 0.001, 0.0001], "ordered": true}}], "values": {"units_1": 20, "regs_1": 0.02, "dropout_1": 0.101, "units_2": 152, "regs_2": 0.052000000000000005, "dropout_2": 0.5080000000000003, "units_4": 180, "learning_rate": 0.0001, "tuner/epochs": 13, "tuner/initial_epoch": 4, "tuner/bracket": 2, "tuner/round": 1, "tuner/trial_id": "4e15d7bd56edb1db85de342f0b6d87ec"}}, "metrics": {"metrics": {"loss": {"direction": "min", "observations": [{"value": [3.2513723373413086], "step": 0}]}, "accuracy": {"direction": "max", "observations": [{"value": [0.7401086091995239], "step": 0}]}, "val_loss": {"direction": "min", "observations": [{"value": [2.7467963695526123], "step": 0}]}, "val_accuracy": {"direction": "max", "observations": [{"value": [0.6929824352264404], "step": 0}]}}}, "score": 0.6929824352264404, "best_step": 0, "status": "COMPLETED"}