{"trial_id": "6877bae4212f18fde2be44a466cf5f6e", "hyperparameters": {"space": [{"class_name": "Int", "config": {"name": "units_1", "default": null, "conditions": [], "min_value": 32, "max_value": 156, "step": 4, "sampling": null}}, {"class_name": "Float", "config": {"name": "regs_1", "default": 0.001, "conditions": [], "min_value": 0.001, "max_value": 0.1, "step": 0.001, "sampling": null}}, {"class_name": "Float", "config": {"name": "dropout_1", "default": 0.1, "conditions": [], "min_value": 0.1, "max_value": 0.8, "step": 0.001, "sampling": null}}, {"class_name": "Int", "config": {"name": "units_2", "default": null, "conditions": [], "min_value": 32, "max_value": 156, "step": 4, "sampling": null}}, {"class_name": "Float", "config": {"name": "regs_2", "default": 0.001, "conditions": [], "min_value": 0.001, "max_value": 0.1, "step": 0.001, "sampling": null}}, {"class_name": "Float", "config": {"name": "dropout_2", "default": 0.1, "conditions": [], "min_value": 0.1, "max_value": 0.8, "step": 0.001, "sampling": null}}, {"class_name": "Int", "config": {"name": "units_4", "default": null, "conditions": [], "min_value": 32, "max_value": 156, "step": 4, "sampling": null}}], "values": {"units_1": 156, "regs_1": 0.016, "dropout_1": 0.7020000000000005, "units_2": 48, "regs_2": 0.024, "dropout_2": 0.27600000000000013, "units_4": 44, "tuner/epochs": 110, "tuner/initial_epoch": 28, "tuner/bracket": 1, "tuner/round": 1, "tuner/trial_id": "fc18b253b7792c8df3a76070bc12fb74"}}, "metrics": {"metrics": {"loss": {"direction": "min", "observations": [{"value": [3.5595638751983643], "step": 0}]}, "accuracy": {"direction": "max", "observations": [{"value": [0.8408839702606201], "step": 0}]}, "val_loss": {"direction": "min", "observations": [{"value": [3.2050106525421143], "step": 0}]}, "val_accuracy": {"direction": "max", "observations": [{"value": [0.8190954923629761], "step": 0}]}}}, "score": 0.8190954923629761, "best_step": 0, "status": "COMPLETED"}